{
  "id": 1234500,
  "ownerId": 77815229,
  "substituteDocumentId": 40114552,
  "actualVersion": {
    "id": 22,
    "name": "Example document",
    "templateId": 1234500,
    "template": {
      "id": 1234500,
      "name": "Example template",
      "attributes": [
        {
          "id": 89268332,
          "typeId": 1,
          "name": "solid state",
          "attributeData": {
            "rows": [
              {
                "name": "Valley",
                "columns": [
                  {
                    "id": 12999199,
                    "isLocked": false,
                    "typeId": 1
                  },
                  {
                    "id": 70946490,
                    "isLocked": false,
                    "typeId": 1
                  }
                ]
              }
            ],
            "headers": [
              {
                "name": "Turkmenistan"
              },
              {
                "name": "Check"
              }
            ]
          }
        }
      ]
    },
    "labelIds": [
      74100572,
      59311714
    ],
    "fileIds": [
      1
    ],
    "files": [
      {
        "id": 1,
        "name": "file1",
        "url": "http://example.com/files/file1.png"
      }
    ],
    "labels": [
      {
        "id": 74100572,
        "name": "Example label",
        "createdAt": 366096,
        "updatedAt": 46726355
      },
      {
        "id": 13379697,
        "name": "wireless",
        "createdAt": 40410480,
        "updatedAt": 53139431
      }
    ],
    "comment": "Lorem ipsum dolor sit amet.",
    "attributeValues": [
      {
        "id": 1234501,
        "type": "string",
        "value": "Example attribute value"
      },
      {
        "id": 1234502,
        "type": "string",
        "value": "Empty value"
      },
      {
        "id": 1234503,
        "type": "string",
        "value": "Cell value 1"
      },
      {
        "id": 1234504,
        "type": "integer",
        "value": 100
      }
    ],
    "createdAt": 88572716,
    "updatedAt": 54133883
  },
  "owner": {
    "id": 95877757,
    "fullName": "Granite",
    "email": "Eldon97@gmail.com",
    "templatesIds": [
      1234500,
      23348181
    ]
  },
  "version": 22,
  "createdAt": 88572716,
  "updatedAt": 54133883
}